misic/MiSiCv2.h5
misic/__init__.py
misic/extras.py
misic/misic.py
misic/utils.py
misic-1.1.5.dist-info/LICENSE
misic-1.1.5.dist-info/METADATA
misic-1.1.5.dist-info/WHEEL
misic-1.1.5.dist-info/entry_points.txt
misic-1.1.5.dist-info/top_level.txt
misic-1.1.5.dist-info/RECORD
