Metadata-Version: 2.1
Name: misic
Version: 1.1.5
Summary: Microbe segmentation in dense colonies
Home-page: https://imm.cnrs.fr
Author: S.Panigrahi, IMM 
Author-email: spanigrahi@imm.cnrs.fr
License: UNKNOWN
Platform: UNKNOWN
Classifier: Programming Language :: Python :: 3
Classifier: License :: OSI Approved :: MIT License
Classifier: Operating System :: OS Independent
Requires-Python: >=3.6
License-File: LICENSE
Requires-Dist: h5py
Requires-Dist: scikit-image
Requires-Dist: tensorflow (==2.4.1)
Requires-Dist: tqdm
